cuda_guass_normal/__init__.py
cuda_guass_normal/cuda_add.py
cuda_guass_normal/cuda_correlation.py
cuda_guass_normal/cuda_cut.py
cuda_guass_normal/cuda_mean.py
cuda_guass_normal/cuda_var.py
cuda_guass_normal/guass_normal.py
cuda_guass_normal-1.13.dist-info/LICENSE
cuda_guass_normal-1.13.dist-info/METADATA
cuda_guass_normal-1.13.dist-info/WHEEL
cuda_guass_normal-1.13.dist-info/top_level.txt
cuda_guass_normal-1.13.dist-info/RECORD
