Metadata-Version: 2.1
Name: cuda-guass-normal
Version: 1.13
Summary: A package used in DNN trainning in ATLAS analysis
Home-page: UNKNOWN
Author: shuzhouz
Author-email: shuzhouz@umich.edu
License: MIT
Platform: UNKNOWN
Requires-Python: >=3.6
